ITHscore/ITHscore.py
ITHscore/__init__.py
ITHscore/assist.py
ITHscore/calculate.py
ITHscore/clustering.py
ITHscore/features.py
ITHscore/load.py
ITHscore/locate.py
ITHscore-0.1.5.dist-info/LICENSE
ITHscore-0.1.5.dist-info/METADATA
ITHscore-0.1.5.dist-info/WHEEL
ITHscore-0.1.5.dist-info/top_level.txt
ITHscore-0.1.5.dist-info/RECORD
