Metadata-Version: 2.1
Name: ITHscore
Version: 0.1.5
Summary: package for calculating ITHscore from CT image
Home-page: https://github.com/pypa/sampleproject
Author: Jackie Li
Author-email: lijiaqi199609@sina.com
License: MIT
Platform: UNKNOWN
License-File: LICENSE
Requires-Dist: numpy (>=1.17.0)
Requires-Dist: matplotlib (>=3.1.3)
Requires-Dist: scikit-learn (>=0.23.2)
Requires-Dist: scipy (>=)
Requires-Dist: six (>=1.5.2)
Requires-Dist: SimpleITK (>=1.2.4)
Requires-Dist: pyradiomics (>=3.0)
